cipenum/__init__.py
cipenum/file_type.py
cipenum/ladder_type.py
cipenum/subtitle_mode.py
cipenum/transcoder_name.py
cipenum/workflow_status.py
cipenum-0.0.3.dist-info/METADATA
cipenum-0.0.3.dist-info/WHEEL
cipenum-0.0.3.dist-info/top_level.txt
cipenum-0.0.3.dist-info/RECORD
