Metadata-Version: 2.1
Name: cipenum
Version: 0.0.3
Summary: CIP ENUms
Home-page: UNKNOWN
Author: Rodrigo Biassusi
Author-email: rodrigio.biassusi@stormsec.com.br
License: MIT
Platform: UNKNOWN
